typeclasses/__init__.py
typeclasses/afunctor.py
typeclasses/decorator.py
typeclasses/functor.py
typeclasses/hash.py
typeclasses/json.py
typeclasses/py.typed
typeclasses-0.2.1.dist-info/LICENSE
typeclasses-0.2.1.dist-info/METADATA
typeclasses-0.2.1.dist-info/WHEEL
typeclasses-0.2.1.dist-info/RECORD
