Metadata-Version: 2.1
Name: typeclasses
Version: 0.2.1
Summary: Extensible methods a la Haskell's typeclasses.
Home-page: https://github.com/thejohnfreeman/python-typeclasses/
License: ISC
Author: John Freeman
Author-email: jfreeman08@gmail.com
Requires-Python: >=3.8,<4.0
Classifier: License :: OSI Approved
Classifier: Programming Language :: Python :: 3
Classifier: Programming Language :: Python :: 3.8
Classifier: Programming Language :: Python :: 3.9
Classifier: Programming Language :: Python :: 3.10
Classifier: Programming Language :: Python :: 3.11
Project-URL: Documentation, https://python-typeclasses.readthedocs.io/
Project-URL: Repository, https://github.com/thejohnfreeman/python-typeclasses/
